{
    "hero_0": {
        "name": "Dariusz Matysiuk",     //Imię Nazwisko
        "class": "Teacher",             //Klasa (1AT,1BT,1CT)
        "number": "0",                  //Numer w dzienniku
        "atributes": [
            { "atributes_type": "birdthDate", "value": "29-07-1978" },  //Data urodzenia
            { "atributes_type": "country", "value": "Poland" },         //Państwo
            { "atributes_type": "city", "value": "Białystok"}           //Miasto
            { "atributes_type": "power", "value": "1"}                //Moc :) 
        ]
    }
}
{
    "hero_1": {
        "name": "Dariusz Matysiuk 1",     //Imię Nazwisko
        "class": "Teacher",             //Klasa (1AT,1BT,1CT)
        "number": "001",                  //Numer w dzienniku
        "atributes": [
            { "atributes_type": "birdthDate", "value": "29-07-1978" },  //Data urodzenia
            { "atributes_type": "country", "value": "Poland" },         //Państwo
            { "atributes_type": "city", "value": "Białystok"}           //Miasto
            { "atributes_type": "power", "value": "inf"}                //Moc :) 
        ]
    }
}
{
    "hero_2": {
        "name": "Paweł Fabrycki",     //Imię Nazwisko
        "class": "1bT",             //Klasa (1AT,1BT,1CT)
        "number": "08",                  //Numer w dzienniku
        "atributes": [
            { "atributes_type": "birdthDate", "value": "23-10-2008" },  //Data urodzenia
            { "atributes_type": "country", "value": "Poland" },         //Państwo
            { "atributes_type": "city", "value": "Wasilków"}           //Miasto
            { "atributes_type": "power", "value": "programming in JavaScript"}                //Moc :)
        ]
    }
}
